Workbook

Sheet ReadMe
A1: MASTER PAINTING AND MAINTENANCE AND DESIGN PTY LTD — ANZ Business Essentials (BSB 012-233, Acct 6542-14278)
A2: DRAFT ONLY — [Unverified: Registered Tax Agent to confirm]. This workbook never lodges anything; all figures are proposals.
A4: RULES APPLIED (locked): GST candidate = amount/11 for GST-inclusive business expenses only; interest/fees/wages/transfers = 0.
A5: Dedup: content-hash txn_id (account|date|desc|amounts|balance). Re-ingesting the same statement cannot create duplicates.
A6: Reconciliation: every statement passed opening + deposits - withdrawals = closing, and per-row running balance (316/316 rows).
A8: LEGEND: yellow cells = draft values awaiting OWNER verdict (category/scope). Blue text = hardcoded inputs. Black = formulas.
A9: Sheets: Ledger (all txns) · Registry (statements + gaps) · Monthly · Categories · Flags · Recon.
A10: Source: 5 original ANZ statement PDFs (canonical copies in Statements/), parsed 2026-07-13 by FinOS ingest per blueprint §5.
A11: Coverage gaps: statements #1-3, #5-7, #9-22, #25 NOT provided — obtain from ANZ to complete FY2024-25 and FY2025-26.

Sheet Ledger
A1: txn_id | B1: date | C1: stmt | D1: description | E1: withdrawal | F1: deposit | G1: balance | H1: category_draft | I1: scope | J1: confidence | K1: gst_applicable | L1: gst_candidate | M1: flags | N1: needs_review | O1: month
A2: ANZ-BE-537c99451cbc | B2: 45372 | C2: 4 | D2: VISA DEBIT PURCHASE CARD 5746 | 7-ELEVEN 2025 NORTH ROCKS | EFFECTIVE DATE 19 MAR 2024 | E2: 107.64 | F2: 0 | G2: 2669.57 | H2: Fuel | I2: business | J2: 0.7 | K2: Y | L2: =IF($K2="Y",ROUND($E2/11,2),0) -> 9.79 | N2: N | O2: 2024-03
A3: ANZ-BE-314dcf290c16 | B3: 45372 | C3: 4 | D3: EFTPOS | ASTEC PAINTS AUST ALEXANDRIA NSWAU | E3: 384.29 | F3: 0 | G3: 2285.28 | H3: Materials-Tools | I3: business | J3: 0.8 | K3: Y | L3: =IF($K3="Y",ROUND($E3/11,2),0) -> 34.94 | N3: N | O3: 2024-03
A4: ANZ-BE-398c9c00bcf4 | B4: 45376 | C4: 4 | D4: ANZ MOBILE BANKING PAYMENT 581694 | TO ARMIN MOHEBIAFZAP | EFFECTIVE DATE 23 MAR 2024 | E4: 500 | F4: 0 | G4: 1785.28 | H4: Associate-Payment | I4: [OPEN] | J4: 0.7 | K4: N | L4: =IF($K4="Y",ROUND($E4/11,2),0) -> 0 | M4: ASSOCIATE:Armin;DIV7A-CANDIDATE | N4: Y | O4: 2024-03
A5: ANZ-BE-b1a65481cf1e | B5: 45377 | C5: 4 | D5: ANZ MOBILE BANKING PAYMENT 088730 | TO ARMIN MOHEBIAFZAP | E5: 100 | F5: 0 | G5: 1685.28 | H5: Associate-Payment | I5: [OPEN] | J5: 0.7 | K5: N | L5: =IF($K5="Y",ROUND($E5/11,2),0) -> 0 | M5: ASSOCIATE:Armin;DIV7A-CANDIDATE | N5: Y | O5: 2024-03
A6: ANZ-BE-0047cdc2e66a | B6: 45377 | C6: 4 | D6: ANZ MOBILE BANKING PAYMENT 583363 | TO ARMIN MOHEBIAFZAP | E6: 150 | F6: 0 | G6: 1535.28 | H6: Associate-Payment | I6: [OPEN] | J6: 0.7 | K6: N | L6: =IF($K6="Y",ROUND($E6/11,2),0) -> 0 | M6: ASSOCIATE:Armin;DIV7A-CANDIDATE | N6: Y | O6: 2024-03
A7: ANZ-BE-efb9333410e8 | B7: 45377 | C7: 4 | D7: ANZ MOBILE BANKING PAYMENT 746999 | TO ARMIN MOHEBIAFZAP | E7: 400 | F7: 0 | G7: 1135.28 | H7: Associate-Payment | I7: [OPEN] | J7: 0.7 | K7: N | L7: =IF($K7="Y",ROUND($E7/11,2),0) -> 0 | M7: ASSOCIATE:Armin;DIV7A-CANDIDATE | N7: Y | O7: 2024-03
A8: ANZ-BE-7bead8d82347 | B8: 45378 | C8: 4 | D8: ANZ MOBILE BANKING PAYMENT 062502 | TO ARMIN MOHEBIAFZAP | E8: 200 | F8: 0 | G8: 935.28 | H8: Associate-Payment | I8: [OPEN] | J8: 0.7 | K8: N | L8: =IF($K8="Y",ROUND($E8/11,2),0) -> 0 | M8: ASSOCIATE:Armin;DIV7A-CANDIDATE | N8: Y | O8: 2024-03
A9: ANZ-BE-6ef45a0cfab1 | B9: 45379 | C9: 4 | D9: VISA DEBIT PURCHASE CARD 5746 | COLES EXPRESS 1639 BAULKHAM H | EFFECTIVE DATE 26 MAR 2024 | E9: 110.41 | F9: 0 | G9: 824.87 | H9: Fuel | I9: business | J9: 0.7 | K9: Y | L9: =IF($K9="Y",ROUND($E9/11,2),0) -> 10.04 | N9: N | O9: 2024-03
A10: ANZ-BE-af3fe96aef35 | B10: 45384 | C10: 4 | D10: PAYMENT FROM SCHONBERGER | INV 22 40% | EFFECTIVE DATE 01 APR 2024 | E10: 0 | F10: 9460 | G10: 10284.87 | H10: Income-Candidate | I10: business | J10: 0.55 | K10: N | L10: =IF($K10="Y",ROUND($E10/11,2),0) -> 0 | N10: Y | O10: 2024-04
A11: ANZ-BE-64a8a265a197 | B11: 45384 | C11: 4 | D11: ANZ MOBILE BANKING PAYMENT 139859 | TO ARMIN MOHEBIAFZAP | EFFECTIVE DATE 29 MAR 2024 | E11: 150 | F11: 0 | G11: 10134.87 | H11: Associate-Payment | I11: [OPEN] | J11: 0.7 | K11: N | L11: =IF($K11="Y",ROUND($E11/11,2),0) -> 0 | M11: ASSOCIATE:Armin;DIV7A-CANDIDATE | N11: Y | O11: 2024-04
A12: ANZ-BE-ba0dcd18960a | B12: 45384 | C12: 4 | D12: ANZ MOBILE BANKING PAYMENT 206793 | TO ARMIN MOHEBIAFZAP | EFFECTIVE DATE 30 MAR 2024 | E12: 670 | F12: 0 | G12: 9464.87 | H12: Associate-Payment | I12: [OPEN] | J12: 0.7 | K12: N | L12: =IF($K12="Y",ROUND($E12/11,2),0) -> 0 | M12: ASSOCIATE:Armin;DIV7A-CANDIDATE | N12: Y | O12: 2024-04
A13: ANZ-BE-840be53a709a | B13: 45384 | C13: 4 | D13: ANZ MOBILE BANKING PAYMENT 908897 | TO ARMIN MOHEBIAFZAP | E13: 1173 | F13: 0 | G13: 8291.87 | H13: Associate-Payment | I13: [OPEN] | J13: 0.7 | K13: N | L13: =IF($K13="Y",ROUND($E13/11,2),0) -> 0 | M13: ASSOCIATE:Armin;DIV7A-CANDIDATE | N13: Y | O13: 2024-04
A14: ANZ-BE-b1e61b4e660a | B14: 45385 | C14: 4 | D14: ANZ MOBILE BANKING PAYMENT 405863 | TO ARMIN MOHEBIAFZAP | E14: 50 | F14: 0 | G14: 8241.87 | H14: Associate-Payment | I14: [OPEN] | J14: 0.7 | K14: N | L14: =IF($K14="Y",ROUND($E14/11,2),0) -> 0 | M14: ASSOCIATE:Armin;DIV7A-CANDIDATE | N14: Y | O14: 2024-04
A15: ANZ-BE-bdd663851062 | B15: 45385 | C15: 4 | D15: ANZ MOBILE BANKING PAYMENT 407124 | TO ARMIN MOHEBIAFZAP | E15: 500 | F15: 0 | G15: 7741.87 | H15: Associate-Payment | I15: [OPEN] | J15: 0.7 | K15: N | L15: =IF($K15="Y",ROUND($E15/11,2),0) -> 0 | M15: ASSOCIATE:Armin;DIV7A-CANDIDATE | N15: Y | O15: 2024-04
A16: ANZ-BE-57b08f0da702 | B16: 45386 | C16: 4 | D16: VISA DEBIT PURCHASE CARD 5746 | GOOGLE ADS7165786750 SYDNEY | EFFECTIVE DATE 02 APR 2024 | E16: 97.29 | F16: 0 | G16: 7644.58 | H16: Software-Subscriptions | I16: business | J16: 0.6 | K16: Y | L16: =IF($K16="Y",ROUND($E16/11,2),0) -> 8.84 | N16: Y | O16: 2024-04
A17: ANZ-BE-e5d7646a95fc | B17: 45386 | C17: 4 | D17: ANZ MOBILE BANKING PAYMENT 160491 | TO ARMIN MOHEBIAFZAP | E17: 600 | F17: 0 | G17: 7044.58 | H17: Associate-Payment | I17: [OPEN] | J17: 0.7 | K17: N | L17: =IF($K17="Y",ROUND($E17/11,2),0) -> 0 | M17: ASSOCIATE:Armin;DIV7A-CANDIDATE | N17: Y | O17: 2024-04
A18: ANZ-BE-433634a4821b | B18: 45387 | C18: 4 | D18: ANZ MOBILE BANKING PAYMENT 380416 | TO ARMIN MOHEBIAFZAP | E18: 20 | F18: 0 | G18: 7024.58 | H18: Associate-Payment | I18: [OPEN] | J18: 0.7 | K18: N | L18: =IF($K18="Y",ROUND($E18/11,2),0) -> 0 | M18: ASSOCIATE:Armin;DIV7A-CANDIDATE | N18: Y | O18: 2024-04
A19: ANZ-BE-3a8c1122881c | B19: 45387 | C19: 4 | D19: ANZ MOBILE BANKING PAYMENT 600546 | TO ARMIN MOHEBIAFZAP | E19: 35 | F19: 0 | G19: 6989.58 | H19: Associate-Payment | I19: [OPEN] | J19: 0.7 | K19: N | L19: =IF($K19="Y",ROUND($E19/11,2),0) -> 0 | M19: ASSOCIATE:Armin;DIV7A-CANDIDATE | N19: Y | O19: 2024-04
A20: ANZ-BE-889748af6844 | B20: 45387 | C20: 4 | D20: ANZ MOBILE BANKING PAYMENT 619003 | TO ARMIN MOHEBIAFZAP | E20: 1000 | F20: 0 | G20: 5989.58 | H20: Associate-Payment | I20: [OPEN] | J20: 0.7 | K20: N | L20: =IF($K20="Y",ROUND($E20/11,2),0) -> 0 | M20: ASSOCIATE:Armin;DIV7A-CANDIDATE | N20: Y | O20: 2024-04
A21: ANZ-BE-0e4eabd6d4fe | B21: 45390 | C21: 4 | D21: ANZ MOBILE BANKING PAYMENT 106180 | TO ARMIN MOHEBIAFZAP | EFFECTIVE DATE 07 APR 2024 | E21: 35 | F21: 0 | G21: 5954.58 | H21: Associate-Payment | I21: [OPEN] | J21: 0.7 | K21: N | L21: =IF($K21="Y",ROUND($E21/11,2),0) -> 0 | M21: ASSOCIATE:Armin;DIV7A-CANDIDATE | N21: Y | O21: 2024-04
A22: ANZ-BE-addb5449fe28 | B22: 45390 | C22: 4 | D22: VISA DEBIT PURCHASE CARD 5746 | EG GROUP/41-45 THIRD AVE BLACKTOWN | EFFECTIVE DATE 06 APR 2024 | E22: 94.92 | F22: 0 | G22: 5859.66 | H22: Fuel | I22: business | J22: 0.7 | K22: Y | L22: =IF($K22="Y",ROUND($E22/11,2),0) -> 8.63 | N22: N | O22: 2024-04
A23: ANZ-BE-8627d9990e3a | B23: 45390 | C23: 4 | D23: ANZ MOBILE BANKING PAYMENT 277967 | TO ARMIN MOHEBIAFZAP | EFFECTIVE DATE 06 APR 2024 | E23: 100 | F23: 0 | G23: 5759.66 | H23: Associate-Payment | I23: [OPEN] | J23: 0.7 | K23: N | L23: =IF($K23="Y",ROUND($E23/11,2),0) -> 0 | M23: ASSOCIATE:Armin;DIV7A-CANDIDATE | N23: Y | O23: 2024-04
A24: ANZ-BE-85e0865e1a7e | B24: 45390 | C24: 4 | D24: VISA DEBIT PURCHASE CARD 5746 | 7-ELEVEN 2025 NORTH ROCKS | EFFECTIVE DATE 05 APR 2024 | E24: 102.45 | F24: 0 | G24: 5657.21 | H24: Fuel | I24: business | J24: 0.7 | K24: Y | L24: =IF($K24="Y",ROUND($E24/11,2),0) -> 9.31 | N24: N | O24: 2024-04
A25: ANZ-BE-6558d64f53b6 | B25: 45390 | C25: 4 | D25: ANZ MOBILE BANKING PAYMENT 668260 | TO ARMIN MOHEBIAFZAP | EFFECTIVE DATE 06 APR 2024 | E25: 200 | F25: 0 | G25: 5457.21 | H25: Associate-Payment | I25: [OPEN] | J25: 0.7 | K25: N | L25: =IF($K25="Y",ROUND($E25/11,2),0) -> 0 | M25: ASSOCIATE:Armin;DIV7A-CANDIDATE | N25: Y | O25: 2024-04
A26: ANZ-BE-635fddc6171d | B26: 45390 | C26: 4 | D26: ANZ MOBILE BANKING PAYMENT 711905 | TO ARMIN MOHEBIAFZAP | E26: 250 | F26: 0 | G26: 5207.21 | H26: Associate-Payment | I26: [OPEN] | J26: 0.7 | K26: N | L26: =IF($K26="Y",ROUND($E26/11,2),0) -> 0 | M26: ASSOCIATE:Armin;DIV7A-CANDIDATE | N26: Y | O26: 2024-04
A27: ANZ-BE-42e0a4e35258 | B27: 45390 | C27: 4 | D27: ANZ MOBILE BANKING PAYMENT 919502 | TO ARMIN MOHEBIAFZAP | EFFECTIVE DATE 07 APR 2024 | E27: 400 | F27: 0 | G27: 4807.21 | H27: Associate-Payment | I27: [OPEN] | J27: 0.7 | K27: N | L27: =IF($K27="Y",ROUND($E27/11,2),0) -> 0 | M27: ASSOCIATE:Armin;DIV7A-CANDIDATE | N27: Y | O27: 2024-04
A28: ANZ-BE-b8ba3678d7b0 | B28: 45392 | C28: 4 | D28: VISA DEBIT PURCHASE CARD 5746 | BUNNINGS 339000 CASTLE HILL | EFFECTIVE DATE 07 APR 2024 | E28: 104.55 | F28: 0 | G28: 4702.66 | H28: Materials-Tools | I28: business | J28: 0.8 | K28: Y | L28: =IF($K28="Y",ROUND($E28/11,2),0) -> 9.5 | N28: N | O28: 2024-04
A29: ANZ-BE-7893dcdb3b87 | B29: 45393 | C29: 4 | D29: VISA DEBIT PURCHASE CARD 5746 | DULUX CASTLE HILL CASTLE HILL | EFFECTIVE DATE 06 APR 2024 | E29: 27 | F29: 0 | G29: 4675.66 | H29: Materials-Tools | I29: business | J29: 0.8 | K29: Y | L29: =IF($K29="Y",ROUND($E29/11,2),0) -> 2.45 | N29: N | O29: 2024-04
A30: ANZ-BE-cc12a76203c6 | B30: 45393 | C30: 4 | D30: VISA DEBIT PURCHASE CARD 5746 | 7-ELEVEN 2254 NORTH RYDE | EFFECTIVE DATE 09 APR 2024 | E30: 99.25 | F30: 0 | G30: 4576.41 | H30: Fuel | I30: business | J30: 0.7 | K30: Y | L30: =IF($K30="Y",ROUND($E30/11,2),0) -> 9.02 | N30: N | O30: 2024-04
A31: ANZ-BE-42ce32b76e41 | B31: 45393 | C31: 4 | D31: EFTPOS | ASTEC PAINTS AUST ALEXANDRIA NSWAU | E31: 193.46 | F31: 0 | G31: 4382.95 | H31: Materials-Tools | I31: business | J31: 0.8 | K31: Y | L31: =IF($K31="Y",ROUND($E31/11,2),0) -> 17.59 | N31: N | O31: 2024-04
A32: ANZ-BE-3be1f18ac452 | B32: 45394 | C32: 4 | D32: ANZ MOBILE BANKING PAYMENT 900343 | TO ARMIN MOHEBIAFZAP | E32: 500 | F32: 0 | G32: 3882.95 | H32: Associate-Payment | I32: [OPEN] | J32: 0.7 | K32: N | L32: =IF($K32="Y",ROUND($E32/11,2),0) -> 0 | M32: ASSOCIATE:Armin;DIV7A-CANDIDATE | N32: Y | O32: 2024-04
A33: ANZ-BE-c8281029cc86 | B33: 45397 | C33: 4 | D33: ANZ MOBILE BANKING PAYMENT 358557 | TO ARMIN MOHEBIAFZAP | EFFECTIVE DATE 14 APR 2024 | E33: 30 | F33: 0 | G33: 3852.95 | H33: Associate-Payment | I33: [OPEN] | J33: 0.7 | K33: N | L33: =IF($K33="Y",ROUND($E33/11,2),0) -> 0 | M33: ASSOCIATE:Armin;DIV7A-CANDIDATE | N33: Y | O33: 2024-04
A34: ANZ-BE-da7f9f56614a | B34: 45397 | C34: 4 | D34: ANZ MOBILE BANKING PAYMENT 726883 | TO ARMIN MOHEBIAFZAP | E34: 50 | F34: 0 | G34: 3802.95 | H34: Associate-Payment | I34: [OPEN] | J34: 0.7 | K34: N | L34: =IF($K34="Y",ROUND($E34/11,2),0) -> 0 | M34: ASSOCIATE:Armin;DIV7A-CANDIDATE | N34: Y | O34: 2024-04
A35: ANZ-BE-9ff6c19b445f | B35: 45397 | C35: 4 | D35: VISA DEBIT PURCHASE CARD 5746 | 7-ELEVEN 2219 EPPING | EFFECTIVE DATE 13 APR 2024 | E35: 60.18 | F35: 0 | G35: 3742.77 | H35: Fuel | I35: business | J35: 0.7 | K35: Y | L35: =IF($K35="Y",ROUND($E35/11,2),0) -> 5.47 | N35: N | O35: 2024-04
A36: ANZ-BE-a77532752820 | B36: 45397 | C36: 4 | D36: VISA DEBIT PURCHASE CARD 5746 | SYDNEY-TEHRAN GROUP PL DURAL | EFFECTIVE DATE 12 APR 2024 | E36: 118.44 | F36: 0 | G36: 3624.33 | H36: Misc | I36: [OPEN] | J36: 0.3 | K36: N | L36: =IF($K36="Y",ROUND($E36/11,2),0) -> 0 | N36: Y | O36: 2024-04
A37: ANZ-BE-ced0c3fe5d6c | B37: 45397 | C37: 4 | D37: ANZ MOBILE BANKING PAYMENT 673635 | TO ARMIN MOHEBIAFZAP | EFFECTIVE DATE 13 APR 2024 | E37: 200 | F37: 0 | G37: 3424.33 | H37: Associate-Payment | I37: [OPEN] | J37: 0.7 | K37: N | L37: =IF($K37="Y",ROUND($E37/11,2),0) -> 0 | M37: ASSOCIATE:Armin;DIV7A-CANDIDATE | N37: Y | O37: 2024-04
A38: ANZ-BE-403e5ec83724 | B38: 45397 | C38: 4 | D38: ANZ MOBILE BANKING PAYMENT 142437 | TO ARMIN MOHEBIAFZAP | E38: 1220 | F38: 0 | G38: 2204.33 | H38: Associate-Payment | I38: [OPEN] | J38: 0.7 | K38: N | L38: =IF($K38="Y",ROUND($E38/11,2),0) -> 0 | M38: ASSOCIATE:Armin;DIV7A-CANDIDATE | N38: Y | O38: 2024-04
A39: ANZ-BE-bcebc3fa842e | B39: 45397 | C39: 4 | D39: VISA DEBIT PURCHASE CARD 5746 | SYDNEY-TEHRAN GROUP PL DURAL | EFFECTIVE DATE 12 APR 2024 | E39: 2113.31 | F39: 0 | G39: 91.02 | H39: Misc | I39: [OPEN] | J39: 0.3 | K39: N | L39: =IF($K39="Y",ROUND($E39/11,2),0) -> 0 | N39: Y | O39: 2024-04
A40: ANZ-BE-609c9fd75165 | B40: 45398 | C40: 4 | D40: PAYMENT FROM SCHONBERGER | INV 23 BALANCE | E40: 0 | F40: 7695 | G40: 7786.02 | H40: Income-Candidate | I40: business | J40: 0.55 | K40: N | L40: =IF($K40="Y",ROUND($E40/11,2),0) -> 0 | N40: Y | O40: 2024-04
A41: ANZ-BE-8bda9d34d586 | B41: 45398 | C41: 4 | D41: PAYMENT | TO XEROAUSTRALIAPTY XEROAUINV_PVMME33D | E41: 16 | F41: 0 | G41: 7770.02 | H41: Software-Subscriptions | I41: business | J41: 0.6 | K41: Y | L41: =IF($K41="Y",ROUND($E41/11,2),0) -> 1.45 | N41: Y | O41: 2024-04
A42: ANZ-BE-3034d750fc61 | B42: 45399 | C42: 4 | D42: EFTPOS | COLES EXPRESS 1587 NORTHMEAD AU | E42: 50.17 | F42: 0 | G42: 7719.85 | H42: Fuel | I42: business | J42: 0.7 | K42: Y | L42: =IF($K42="Y",ROUND($E42/11,2),0) -> 4.56 | N42: N | O42: 2024-04
A43: ANZ-BE-ebae936dba64 | B43: 45400 | C43: 4 | D43: VISA DEBIT PURCHASE CARD 5746 | DULUX CASTLE HILL CASTLE HILL | EFFECTIVE DATE 13 APR 2024 | E43: 72.5 | F43: 0 | G43: 7647.35 | H43: Materials-Tools | I43: business | J43: 0.8 | K43: Y | L43: =IF($K43="Y",ROUND($E43/11,2),0) -> 6.59 | N43: N | O43: 2024-04
A44: ANZ-BE-ffe7d0e7ddce | B44: 45401 | C44: 4 | D44: EFTPOS | INSP PAINT CHATSWOOD CHATSWOOD AU | E44: 48.6 | F44: 0 | G44: 7598.75 | H44: Materials-Tools | I44: business | J44: 0.8 | K44: Y | L44: =IF($K44="Y",ROUND($E44/11,2),0) -> 4.42 | N44: N | O44: 2024-04
A45: ANZ-BE-4fee19c81a1f | B45: 45401 | C45: 4 | D45: ANZ MOBILE BANKING PAYMENT 863736 | TO ARMIN MOHEBIAFZAP | E45: 500 | F45: 0 | G45: 7098.75 | H45: Associate-Payment | I45: [OPEN] | J45: 0.7 | K45: N | L45: =IF($K45="Y",ROUND($E45/11,2),0) -> 0 | M45: ASSOCIATE:Armin;DIV7A-CANDIDATE | N45: Y | O45: 2024-04
A46: ANZ-BE-4479aa832708 | B46: 45498 | C46: 8 | D46: PAYMENT | TO TRANSPORT FOR NS ETOLL3825523745 | E46: 25 | F46: 0 | G46: -24.42 | H46: Vehicle-Tolls | I46: business | J46: 0.8 | K46: Y | L46: =IF($K46="Y",ROUND($E46/11,2),0) -> 2.27 | N46: N | O46: 2024-07
A47: ANZ-BE-dc699c099310 | B47: 45499 | C47: 8 | D47: PAYMENT FROM ARMIN MOHEBIAFZAL | E47: 0 | F47: 25 | G47: 0.58 | H47: Associate-Inflow | I47: [OPEN] | J47: 0.6 | K47: N | L47: =IF($K47="Y",ROUND($E47/11,2),0) -> 0 | M47: ASSOCIATE:Armin | N47: Y | O47: 2024-07
A48: ANZ-BE-812281f50822 | B48: 45499 | C48: 8 | D48: PAYMENT FROM ARMIN MOHEBIAFZAL | E48: 0 | F48: 25 | G48: 25.58 | H48: Associate-Inflow | I48: [OPEN] | J48: 0.6 | K48: N | L48: =IF($K48="Y",ROUND($E48/11,2),0) -> 0 | M48: ASSOCIATE:Armin | N48: Y | O48: 2024-07
A49: ANZ-BE-702a2b808462 | B49: 45499 | C49: 8 | D49: PAYMENT | TO TRANSPORT FOR NS ETOLL3826481103 | E49: 25 | F49: 0 | G49: 0.58 | H49: Vehicle-Tolls | I49: business | J49: 0.8 | K49: Y | L49: =IF($K49="Y",ROUND($E49/11,2),0) -> 2.27 | N49: N | O49: 2024-07
A50: ANZ-BE-2d6da07b33c6 | B50: 45502 | C50: 8 | D50: PAYMENT | TO TRANSPORT FOR NS ETOLL3828476540 | E50: 25 | F50: 0 | G50: -24.42 | H50: Vehicle-Tolls | I50: business | J50: 0.8 | K50: Y | L50: =IF($K50="Y",ROUND($E50/11,2),0) -> 2.27 | N50: N | O50: 2024-07
A51: ANZ-BE-6243244dc3f4 | B51: 45503 | C51: 8 | D51: PAYMENT FROM REZA MASHHOORI | E51: 0 | F51: 5250 | G51: 5225.58 | H51: Income-Candidate | I51: business | J51: 0.55 | K51: N | L51: =IF($K51="Y",ROUND($E51/11,2),0) -> 0 | M51: REZA-IDENTITY(OQ7) | N51: Y | O51: 2024-07
A52: ANZ-BE-16ced6ed37e1 | B52: 45503 | C52: 8 | D52: ANZ MOBILE BANKING PAYMENT 250312 | TO ARMIN MOHEBIAFZAP | E52: 600 | F52: 0 | G52: 4625.58 | H52: Associate-Payment | I52: [OPEN] | J52: 0.7 | K52: N | L52: =IF($K52="Y",ROUND($E52/11,2),0) -> 0 | M52: ASSOCIATE:Armin;DIV7A-CANDIDATE | N52: Y | O52: 2024-07
A53: ANZ-BE-1f30fff4f154 | B53: 45503 | C53: 8 | D53: ANZ MOBILE BANKING PAYMENT 040331 | TO ARMIN MOHEBIAFZAP | E53: 1350 | F53: 0 | G53: 3275.58 | H53: Associate-Payment | I53: [OPEN] | J53: 0.7 | K53: N | L53: =IF($K53="Y",ROUND($E53/11,2),0) -> 0 | M53: ASSOCIATE:Armin;DIV7A-CANDIDATE | N53: Y | O53: 2024-07
A54: ANZ-BE-a5281ee3309b | B54: 45504 | C54: 8 | D54: PAYMENT | TO TRANSPORT FOR NS ETOLL3830193427 | E54: 25 | F54: 0 | G54: 3250.58 | H54: Vehicle-Tolls | I54: business | J54: 0.8 | K54: Y | L54: =IF($K54="Y",ROUND($E54/11,2),0) -> 2.27 | N54: N | O54: 2024-07
A55: ANZ-BE-08e79ef7332e | B55: 45504 | C55: 8 | D55: VISA DEBIT PURCHASE CARD 5746 | 7-ELEVEN 2219 EPPING | EFFECTIVE DATE 29 JUL 2024 | E55: 43 | F55: 0 | G55: 3207.58 | H55: Fuel | I55: business | J55: 0.7 | K55: Y | L55: =IF($K55="Y",ROUND($E55/11,2),0) -> 3.91 | N55: N | O55: 2024-07
A56: ANZ-BE-3ea633544850 | B56: 45504 | C56: 8 | D56: ANZ MOBILE BANKING PAYMENT 974401 | TO ARMIN MOHEBIAFZAP | E56: 580 | F56: 0 | G56: 2627.58 | H56: Associate-Payment | I56: [OPEN] | J56: 0.7 | K56: N | L56: =IF($K56="Y",ROUND($E56/11,2),0) -> 0 | M56: ASSOCIATE:Armin;DIV7A-CANDIDATE | N56: Y | O56: 2024-07
A57: ANZ-BE-bf1632808b88 | B57: 45504 | C57: 8 | D57: ANZ MOBILE BANKING PAYMENT 973585 | TO ARMIN MOHEBIAFZAP | E57: 600 | F57: 0 | G57: 2027.58 | H57: Associate-Payment | I57: [OPEN] | J57: 0.7 | K57: N | L57: =IF($K57="Y",ROUND($E57/11,2),0) -> 0 | M57: ASSOCIATE:Armin;DIV7A-CANDIDATE | N57: Y | O57: 2024-07
A58: ANZ-BE-412f2d05bc23 | B58: 45504 | C58: 8 | D58: DEBIT INTEREST CHARGED | E58: 0.18 | F58: 0 | G58: 2027.4 | H58: Bank-Interest-Fees | I58: business | J58: 0.85 | K58: N | L58: =IF($K58="Y",ROUND($E58/11,2),0) -> 0 | N58: N | O58: 2024-07
A59: ANZ-BE-bf8aa81eda58 | B59: 45505 | C59: 8 | D59: EFTPOS | COLES EXPRESS 1639 BAULKHAM H AU | E59: 123.01 | F59: 0 | G59: 1904.39 | H59: Fuel | I59: business | J59: 0.7 | K59: Y | L59: =IF($K59="Y",ROUND($E59/11,2),0) -> 11.18 | N59: N | O59: 2024-08
A60: ANZ-BE-0d82035b0e34 | B60: 45505 | C60: 8 | D60: VISA DEBIT PURCHASE CARD 5746 | CASTLE HILL PAINT GA CASTLE HILL | EFFECTIVE DATE 30 JUL 2024 | E60: 468.52 | F60: 0 | G60: 1435.87 | H60: Materials-Tools | I60: business | J60: 0.8 | K60: Y | L60: =IF($K60="Y",ROUND($E60/11,2),0) -> 42.59 | N60: N | O60: 2024-08
A61: ANZ-BE-0f52d7312714 | B61: 45509 | C61: 8 | D61: ANZ MOBILE BANKING PAYMENT 741096 | TO ARMIN MOHEBIAFZAP | EFFECTIVE DATE 04 AUG 2024 | E61: 50 | F61: 0 | G61: 1385.87 | H61: Associate-Payment | I61: [OPEN] | J61: 0.7 | K61: N | L61: =IF($K61="Y",ROUND($E61/11,2),0) -> 0 | M61: ASSOCIATE:Armin;DIV7A-CANDIDATE | N61: Y | O61: 2024-08
A62: ANZ-BE-dda04aceb2c6 | B62: 45509 | C62: 8 | D62: VISA DEBIT PURCHASE CARD 5746 | BUNNINGS 579000 NARRABEEN | EFFECTIVE DATE 01 AUG 2024 | E62: 53.96 | F62: 0 | G62: 1331.91 | H62: Materials-Tools | I62: business | J62: 0.8 | K62: Y | L62: =IF($K62="Y",ROUND($E62/11,2),0) -> 4.91 | N62: N | O62: 2024-08
A63: ANZ-BE-85a7d215af5e | B63: 45510 | C63: 8 | D63: ANZ MOBILE BANKING PAYMENT 819805 | TO ARMIN MOHEBIAFZAP | E63: 60 | F63: 0 | G63: 1271.91 | H63: Associate-Payment | I63: [OPEN] | J63: 0.7 | K63: N | L63: =IF($K63="Y",ROUND($E63/11,2),0) -> 0 | M63: ASSOCIATE:Armin;DIV7A-CANDIDATE | N63: Y | O63: 2024-08
A64: ANZ-BE-ecf0c53d0534 | B64: 45511 | C64: 8 | D64: ANZ MOBILE BANKING PAYMENT 928936 | TO ARMIN MOHEBIAFZAP | E64: 1000 | F64: 0 | G64: 271.91 | H64: Associate-Payment | I64: [OPEN] | J64: 0.7 | K64: N | L64: =IF($K64="Y",ROUND($E64/11,2),0) -> 0 | M64: ASSOCIATE:Armin;DIV7A-CANDIDATE | N64: Y | O64: 2024-08
A65: ANZ-BE-7f1129d6f26c | B65: 45513 | C65: 8 | D65: PAYMENT FROM MOMENTUM PROJECT GROUP PTY | MP DESIGN PTY LTD | E65: 0 | F65: 9350 | G65: 9621.91 | H65: Income-Candidate | I65: business | J65: 0.55 | K65: N | L65: =IF($K65="Y",ROUND($E65/11,2),0) -> 0 | N65: Y | O65: 2024-08
A66: ANZ-BE-a3d7a69c0a5c | B66: 45513 | C66: 8 | D66: ANZ MOBILE BANKING PAYMENT 281384 | TO ARMIN MOHEBIAFZAP | E66: 69 | F66: 0 | G66: 9552.91 | H66: Associate-Payment | I66: [OPEN] | J66: 0.7 | K66: N | L66: =IF($K66="Y",ROUND($E66/11,2),0) -> 0 | M66: ASSOCIATE:Armin;DIV7A-CANDIDATE | N66: Y | O66: 2024-08
A67: ANZ-BE-a3426f5ed72f | B67: 45513 | C67: 8 | D67: VISA DEBIT PURCHASE CARD 5746 | BP NORTH ROCKS NORTH ROCKS | EFFECTIVE DATE 06 AUG 2024 | E67: 102.82 | F67: 0 | G67: 9450.09 | H67: Fuel | I67: business | J67: 0.7 | K67: Y | L67: =IF($K67="Y",ROUND($E67/11,2),0) -> 9.35 | N67: N | O67: 2024-08
A68: ANZ-BE-979f762ab4a8 | B68: 45513 | C68: 8 | D68: ANZ MOBILE BANKING PAYMENT 088103 | TO ARMIN MOHEBIAFZAP | E68: 600 | F68: 0 | G68: 8850.09 | H68: Associate-Payment | I68: [OPEN] | J68: 0.7 | K68: N | L68: =IF($K68="Y",ROUND($E68/11,2),0) -> 0 | M68: ASSOCIATE:Armin;DIV7A-CANDIDATE | N68: Y | O68: 2024-08
A69: ANZ-BE-191165ace546 | B69: 45516 | C69: 8 | D69: VISA DEBIT PURCHASE CARD 5746 | 7-ELEVEN 2025 NORTH ROCKS | EFFECTIVE DATE 10 AUG 2024 | E69: 106.56 | F69: 0 | G69: 8743.53 | H69: Fuel | I69: business | J69: 0.7 | K69: Y | L69: =IF($K69="Y",ROUND($E69/11,2),0) -> 9.69 | N69: N | O69: 2024-08
A70: ANZ-BE-6949a4a5647b | B70: 45516 | C70: 8 | D70: ANZ MOBILE BANKING PAYMENT 235131 | TO ARMIN MOHEBIAFZAP | EFFECTIVE DATE 10 AUG 2024 | E70: 400 | F70: 0 | G70: 8343.53 | H70: Associate-Payment | I70: [OPEN] | J70: 0.7 | K70: N | L70: =IF($K70="Y",ROUND($E70/11,2),0) -> 0 | M70: ASSOCIATE:Armin;DIV7A-CANDIDATE | N70: Y | O70: 2024-08
A71: ANZ-BE-214d85680b87 | B71: 45516 | C71: 8 | D71: ANZ MOBILE BANKING PAYMENT 936678 | TO ARMIN MOHEBIAFZAP | E71: 700 | F71: 0 | G71: 7643.53 | H71: Associate-Payment | I71: [OPEN] | J71: 0.7 | K71: N | L71: =IF($K71="Y",ROUND($E71/11,2),0) -> 0 | M71: ASSOCIATE:Armin;DIV7A-CANDIDATE | N71: Y | O71: 2024-08
A72: ANZ-BE-59968b1eb807 | B72: 45516 | C72: 8 | D72: ANZ MOBILE BANKING PAYMENT 217281 | TO ARMIN MOHEBIAFZAP | EFFECTIVE DATE 10 AUG 2024 | E72: 1280 | F72: 0 | G72: 6363.53 | H72: Associate-Payment | I72: [OPEN] | J72: 0.7 | K72: N | L72: =IF($K72="Y",ROUND($E72/11,2),0) -> 0 | M72: ASSOCIATE:Armin;DIV7A-CANDIDATE | N72: Y | O72: 2024-08
A73: ANZ-BE-450ff0d3ce3c | B73: 45517 | C73: 8 | D73: VISA DEBIT PURCHASE CARD 5746 | 7-ELEVEN 2205 WEST PENNANT | EFFECTIVE DATE 11 AUG 2024 | E73: 78.84 | F73: 0 | G73: 6284.69 | H73: Fuel | I73: business | J73: 0.7 | K73: Y | L73: =IF($K73="Y",ROUND($E73/11,2),0) -> 7.17 | N73: N | O73: 2024-08
A74: ANZ-BE-cb4ddbae83fd | B74: 45517 | C74: 8 | D74: ANZ MOBILE BANKING PAYMENT 795637 | TO ARMIN MOHEBIAFZAP | E74: 290 | F74: 0 | G74: 5994.69 | H74: Associate-Payment | I74: [OPEN] | J74: 0.7 | K74: N | L74: =IF($K74="Y",ROUND($E74/11,2),0) -> 0 | M74: ASSOCIATE:Armin;DIV7A-CANDIDATE | N74: Y | O74: 2024-08
A75: ANZ-BE-15cf9ea484c1 | B75: 45519 | C75: 8 | D75: ANZ MOBILE BANKING PAYMENT 177290 | TO ARMIN MOHEBIAFZAP | E75: 80 | F75: 0 | G75: 5914.69 | H75: Associate-Payment | I75: [OPEN] | J75: 0.7 | K75: N | L75: =IF($K75="Y",ROUND($E75/11,2),0) -> 0 | M75: ASSOCIATE:Armin;DIV7A-CANDIDATE | N75: Y | O75: 2024-08
A76: ANZ-BE-d0e878878e16 | B76: 45519 | C76: 8 | D76: EFTPOS | COLES EXPRESS 1639 BAULKHAM H AU | E76: 114.66 | F76: 0 | G76: 5800.03 | H76: Fuel | I76: business | J76: 0.7 | K76: Y | L76: =IF($K76="Y",ROUND($E76/11,2),0) -> 10.42 | N76: N | O76: 2024-08
A77: ANZ-BE-2548e3932b5a | B77: 45519 | C77: 8 | D77: ANZ MOBILE BANKING PAYMENT 279375 | TO ARMIN MOHEBIAFZAP | E77: 220 | F77: 0 | G77: 5580.03 | H77: Associate-Payment | I77: [OPEN] | J77: 0.7 | K77: N | L77: =IF($K77="Y",ROUND($E77/11,2),0) -> 0 | M77: ASSOCIATE:Armin;DIV7A-CANDIDATE | N77: Y | O77: 2024-08
A78: ANZ-BE-5116074232d8 | B78: 45519 | C78: 8 | D78: ANZ MOBILE BANKING PAYMENT 410326 | TO ARMIN MOHEBIAFZAP | E78: 380 | F78: 0 | G78: 5200.03 | H78: Associate-Payment | I78: [OPEN] | J78: 0.7 | K78: N | L78: =IF($K78="Y",ROUND($E78/11,2),0) -> 0 | M78: ASSOCIATE:Armin;DIV7A-CANDIDATE | N78: Y | O78: 2024-08
A79: ANZ-BE-5aed4eebe1c8 | B79: 45520 | C79: 8 | D79: ANZ MOBILE BANKING PAYMENT 779805 | TO ARMIN MOHEBIAFZAP | E79: 10 | F79: 0 | G79: 5190.03 | H79: Associate-Payment | I79: [OPEN] | J79: 0.7 | K79: N | L79: =IF($K79="Y",ROUND($E79/11,2),0) -> 0 | M79: ASSOCIATE:Armin;DIV7A-CANDIDATE | N79: Y | O79: 2024-08
A80: ANZ-BE-0cc3e8330fe4 | B80: 45520 | C80: 8 | D80: ANZ MOBILE BANKING PAYMENT 901395 | TO ARMIN MOHEBIAFZAP | E80: 20 | F80: 0 | G80: 5170.03 | H80: Associate-Payment | I80: [OPEN] | J80: 0.7 | K80: N | L80: =IF($K80="Y",ROUND($E80/11,2),0) -> 0 | M80: ASSOCIATE:Armin;DIV7A-CANDIDATE | N80: Y | O80: 2024-08
A81: ANZ-BE-87abb0b16170 | B81: 45520 | C81: 8 | D81: PAYMENT | TO XEROAUSTRALIAPTY XEROAUINV_QFUYPSB3 | E81: 35 | F81: 0 | G81: 5135.03 | H81: Software-Subscriptions | I81: business | J81: 0.6 | K81: Y | L81: =IF($K81="Y",ROUND($E81/11,2),0) -> 3.18 | N81: Y | O81: 2024-08
A82: ANZ-BE-6e81f9eb25d7 | B82: 45523 | C82: 8 | D82: ANZ MOBILE BANKING PAYMENT 548198 | TO ARMIN MOHEBIAFZAP | EFFECTIVE DATE 17 AUG 2024 | E82: 20 | F82: 0 | G82: 5115.03 | H82: Associate-Payment | I82: [OPEN] | J82: 0.7 | K82: N | L82: =IF($K82="Y",ROUND($E82/11,2),0) -> 0 | M82: ASSOCIATE:Armin;DIV7A-CANDIDATE | N82: Y | O82: 2024-08
A83: ANZ-BE-03457cf549e8 | B83: 45523 | C83: 8 | D83: ANZ MOBILE BANKING PAYMENT 836560 | TO ARMIN MOHEBIAFZAP | EFFECTIVE DATE 18 AUG 2024 | E83: 100 | F83: 0 | G83: 5015.03 | H83: Associate-Payment | I83: [OPEN] | J83: 0.7 | K83: N | L83: =IF($K83="Y",ROUND($E83/11,2),0) -> 0 | M83: ASSOCIATE:Armin;DIV7A-CANDIDATE | N83: Y | O83: 2024-08
A84: ANZ-BE-791aee3e86c0 | B84: 45523 | C84: 8 | D84: ANZ MOBILE BANKING PAYMENT 925852 | TO ARMIN MOHEBIAFZAP | EFFECTIVE DATE 18 AUG 2024 | E84: 150 | F84: 0 | G84: 4865.03 | H84: Associate-Payment | I84: [OPEN] | J84: 0.7 | K84: N | L84: =IF($K84="Y",ROUND($E84/11,2),0) -> 0 | M84: ASSOCIATE:Armin;DIV7A-CANDIDATE | N84: Y | O84: 2024-08
A85: ANZ-BE-0a1404d33152 | B85: 45523 | C85: 8 | D85: ANZ MOBILE BANKING PAYMENT 543315 | TO ARMIN MOHEBIAFZAP | E85: 250 | F85: 0 | G85: 4615.03 | H85: Associate-Payment | I85: [OPEN] | J85: 0.7 | K85: N | L85: =IF($K85="Y",ROUND($E85/11,2),0) -> 0 | M85: ASSOCIATE:Armin;DIV7A-CANDIDATE | N85: Y | O85: 2024-08
A86: ANZ-BE-8aa30159170e | B86: 45523 | C86: 8 | D86: VISA DEBIT PURCHASE CARD 5746 | CASTLE HILL PAINT GA CASTLE HILL | EFFECTIVE DATE 16 AUG 2024 | E86: 325 | F86: 0 | G86: 4290.03 | H86: Materials-Tools | I86: business | J86: 0.8 | K86: Y | L86: =IF($K86="Y",ROUND($E86/11,2),0) -> 29.55 | N86: N | O86: 2024-08
A87: ANZ-BE-f9241de668a0 | B87: 45524 | C87: 8 | D87: TRANSFER | FROM BELLE PROPERTY L BELLE LANE COVE | E87: 0 | F87: 2420 | G87: 6710.03 | H87: Income-Candidate | I87: business | J87: 0.55 | K87: N | L87: =IF($K87="Y",ROUND($E87/11,2),0) -> 0 | N87: Y | O87: 2024-08
A88: ANZ-BE-68efad0c96ea | B88: 45524 | C88: 8 | D88: ANZ MOBILE BANKING PAYMENT 589116 | TO ARMIN MOHEBIAFZAP | E88: 1470 | F88: 0 | G88: 5240.03 | H88: Associate-Payment | I88: [OPEN] | J88: 0.7 | K88: N | L88: =IF($K88="Y",ROUND($E88/11,2),0) -> 0 | M88: ASSOCIATE:Armin;DIV7A-CANDIDATE | N88: Y | O88: 2024-08
A89: ANZ-BE-0bbcc03741ad | B89: 45951 | C89: 23 | D89: EFTPOS | CASTLE HILL PAINT GA CASTLE HILL NSWAU | E89: 14 | F89: 0 | G89: 1923.84 | H89: Materials-Tools | I89: business | J89: 0.8 | K89: Y | L89: =IF($K89="Y",ROUND($E89/11,2),0) -> 1.27 | N89: N | O89: 2025-10
A90: ANZ-BE-828496161fb4 | B90: 45951 | C90: 23 | D90: EFTPOS | CASTLE HILL PAINT GA CASTLE HILL NSWAU | E90: 25 | F90: 0 | G90: 1898.84 | H90: Materials-Tools | I90: business | J90: 0.8 | K90: Y | L90: =IF($K90="Y",ROUND($E90/11,2),0) -> 2.27 | N90: N | O90: 2025-10
A91: ANZ-BE-95d8d93af53f | B91: 45952 | C91: 23 | D91: VISA DEBIT PURCHASE CARD 5746 | DULUX BROOKVALE BROOKVALE | EFFECTIVE DATE 18 OCT 2025 | E91: 263.26 | F91: 0 | G91: 1635.58 | H91: Materials-Tools | I91: business | J91: 0.8 | K91: Y | L91: =IF($K91="Y",ROUND($E91/11,2),0) -> 23.93 | N91: N | O91: 2025-10
A92: ANZ-BE-961a62ab31d3 | B92: 45953 | C92: 23 | D92: VISA DEBIT PURCHASE CARD 5746 | BUNNINGS 407000 ROUSE HILL | EFFECTIVE DATE 21 OCT 2025 | E92: 9 | F92: 0 | G92: 1626.58 | H92: Materials-Tools | I92: business | J92: 0.8 | K92: Y | L92: =IF($K92="Y",ROUND($E92/11,2),0) -> 0.82 | N92: N | O92: 2025-10
A93: ANZ-BE-7b399db6f3bc | B93: 45953 | C93: 23 | D93: EFTPOS | CASTLE HILL PAINT GA CASTLE HILL NSWAU | E93: 55 | F93: 0 | G93: 1571.58 | H93: Materials-Tools | I93: business | J93: 0.8 | K93: Y | L93: =IF($K93="Y",ROUND($E93/11,2),0) -> 5 | N93: N | O93: 2025-10
A94: ANZ-BE-d95af561db05 | B94: 45957 | C94: 23 | D94: PAYMENT | TO TRANSPORT FOR NS ETOLL4211626295 | E94: 25 | F94: 0 | G94: 1546.58 | H94: Vehicle-Tolls | I94: business | J94: 0.8 | K94: Y | L94: =IF($K94="Y",ROUND($E94/11,2),0) -> 2.27 | N94: N | O94: 2025-10
A95: ANZ-BE-e150efd28a1e | B95: 45957 | C95: 23 | D95: PAYMENT | TO TRANSPORT FOR NS ETOLL4211677779 | E95: 25 | F95: 0 | G95: 1521.58 | H95: Vehicle-Tolls | I95: business | J95: 0.8 | K95: Y | L95: =IF($K95="Y",ROUND($E95/11,2),0) -> 2.27 | N95: N | O95: 2025-10
A96: ANZ-BE-4d9e46852e0d | B96: 45957 | C96: 23 | D96: VISA DEBIT PURCHASE CARD 5746 | 7-ELEVEN 2205 WEST PENNANT | EFFECTIVE DATE 23 OCT 2025 | E96: 60.45 | F96: 0 | G96: 1461.13 | H96: Fuel | I96: business | J96: 0.7 | K96: Y | L96: =IF($K96="Y",ROUND($E96/11,2),0) -> 5.5 | N96: N | O96: 2025-10
A97: ANZ-BE-3728747828c8 | B97: 45957 | C97: 23 | D97: EFTPOS | BUNNINGS CARLINGFORD 7132\CARLING NSW AU | EFFECTIVE DATE 26 OCT 2025 | E97: 253.77 | F97: 0 | G97: 1207.36 | H97: Materials-Tools | I97: business | J97: 0.8 | K97: Y | L97: =IF($K97="Y",ROUND($E97/11,2),0) -> 23.07 | N97: N | O97: 2025-10
A98: ANZ-BE-6ed45d02044c | B98: 45958 | C98: 23 | D98: EFTPOS | UNITED WILBERFORCE \WILBERFORCE AU | E98: 70 | F98: 0 | G98: 1137.36 | H98: Misc | I98: [OPEN] | J98: 0.3 | K98: N | L98: =IF($K98="Y",ROUND($E98/11,2),0) -> 0 | N98: Y | O98: 2025-10
A99: ANZ-BE-d349a1fb0c36 | B99: 45960 | C99: 23 | D99: VISA DEBIT PURCHASE CARD 5746 | 7-ELEVEN 2128 CARLINGFORD | EFFECTIVE DATE 27 OCT 2025 | E99: 78.48 | F99: 0 | G99: 1058.88 | H99: Fuel | I99: business | J99: 0.7 | K99: Y | L99: =IF($K99="Y",ROUND($E99/11,2),0) -> 7.13 | N99: N | O99: 2025-10
A100: ANZ-BE-62ae1f49f6ac | B100: 45964 | C100: 23 | D100: VISA DEBIT PURCHASE CARD 5746 | FREEDOM FUELS VINEYARD VINEYARD | EFFECTIVE DATE 31 OCT 2025 | E100: 92.21 | F100: 0 | G100: 966.67 | H100: Misc | I100: [OPEN] | J100: 0.3 | K100: N | L100: =IF($K100="Y",ROUND($E100/11,2),0) -> 0 | N100: Y | O100: 2025-11
...

Sheet Registry
A1: stmt_no | B1: canonical_file | C1: period_from | D1: period_to | E1: opening | F1: total_deposits | G1: total_withdrawals | H1: closing | I1: n_txn | J1: sum_dep(Ledger) | K1: sum_wdr(Ledger) | L1: close_check | M1: running_ok | N1: notes
A2: 4 | B2: ANZ-BE_stmt04_2024-03-20_2024-04-19.pdf | C2: 2024-03-20 | D2: 2024-04-19 | E2: 2777.21 | F2: 17155 | G2: 12833.46 | H2: 7098.75 | I2: 44 | J2: =SUMIFS(Ledger!$F:$F,Ledger!$C:$C,$A2) -> 17155 | K2: =SUMIFS(Ledger!$E:$E,Ledger!$C:$C,$A2) -> 12833.46 | L2: =IF(ROUND($E2+$J2-$K2,2)=$H2,"OK","FAIL") -> OK | M2: OK | N2: stmts #1-3 missing before; #5-7 missing after
A3: 8 | B3: ANZ-BE_stmt08_2024-07-19_2024-08-20.pdf | C3: 2024-07-19 | D3: 2024-08-20 | E3: 0.58 | F3: 17070 | G3: 11830.55 | H3: 5240.03 | I3: 43 | J3: =SUMIFS(Ledger!$F:$F,Ledger!$C:$C,$A3) -> 17070 | K3: =SUMIFS(Ledger!$E:$E,Ledger!$C:$C,$A3) -> 11830.55 | L3: =IF(ROUND($E3+$J3-$K3,2)=$H3,"OK","FAIL") -> OK | M3: OK | N3: #9-22 missing after
A4: 23 | B4: ANZ-BE_stmt23_2025-10-20_2025-11-20.pdf | C4: 2025-10-20 | D4: 2025-11-20 | E4: 1937.84 | F4: 6000 | G4: 6444.52 | H4: 1493.32 | I4: 40 | J4: =SUMIFS(Ledger!$F:$F,Ledger!$C:$C,$A4) -> 6000 | K4: =SUMIFS(Ledger!$E:$E,Ledger!$C:$C,$A4) -> 6444.52 | L4: =IF(ROUND($E4+$J4-$K4,2)=$H4,"OK","FAIL") -> OK | M4: OK
A5: 24 | B5: ANZ-BE_stmt24_2025-11-20_2025-12-19.pdf | C5: 2025-11-20 | D5: 2025-12-19 | E5: 1493.32 | F5: 10081.35 | G5: 10569.42 | H5: 1005.25 | I5: 99 | J5: =SUMIFS(Ledger!$F:$F,Ledger!$C:$C,$A5) -> 10081.35 | K5: =SUMIFS(Ledger!$E:$E,Ledger!$C:$C,$A5) -> 10569.42 | L5: =IF(ROUND($E5+$J5-$K5,2)=$H5,"OK","FAIL") -> OK | M5: OK | N5: #25 missing after
A6: 26 | B6: ANZ-BE_stmt26_2026-01-20_2026-02-20.pdf | C6: 2026-01-20 | D6: 2026-02-20 | E6: 695.95 | F6: 18519.53 | G6: 18876.35 | H6: 339.13 | I6: 90 | J6: =SUMIFS(Ledger!$F:$F,Ledger!$C:$C,$A6) -> 18519.53 | K6: =SUMIFS(Ledger!$E:$E,Ledger!$C:$C,$A6) -> 18876.35 | L6: =IF(ROUND($E6+$J6-$K6,2)=$H6,"OK","FAIL") -> OK | M6: OK | N6: latest provided

Sheet Monthly
A1: month | B1: inflow | C1: outflow | D1: net | E1: gst_candidate_sum | F1: n_txns
A2: 2024-03 | B2: =SUMIFS(Ledger!$F:$F,Ledger!$O:$O,$A2) -> 0 | C2: =SUMIFS(Ledger!$E:$E,Ledger!$O:$O,$A2) -> 1952.34 | D2: =$B2-$C2 -> -1952.34 | E2: =SUMIFS(Ledger!$L:$L,Ledger!$O:$O,$A2) -> 54.77 | F2: =COUNTIFS(Ledger!$O:$O,$A2) -> 8
A3: 2024-04 | B3: =SUMIFS(Ledger!$F:$F,Ledger!$O:$O,$A3) -> 17155 | C3: =SUMIFS(Ledger!$E:$E,Ledger!$O:$O,$A3) -> 10881.12 | D3: =$B3-$C3 -> 6273.88 | E3: =SUMIFS(Ledger!$L:$L,Ledger!$O:$O,$A3) -> 87.83 | F3: =COUNTIFS(Ledger!$O:$O,$A3) -> 36
A4: 2024-07 | B4: =SUMIFS(Ledger!$F:$F,Ledger!$O:$O,$A4) -> 5300 | C4: =SUMIFS(Ledger!$E:$E,Ledger!$O:$O,$A4) -> 3273.18 | D4: =$B4-$C4 -> 2026.82 | E4: =SUMIFS(Ledger!$L:$L,Ledger!$O:$O,$A4) -> 12.99 | F4: =COUNTIFS(Ledger!$O:$O,$A4) -> 13
A5: 2024-08 | B5: =SUMIFS(Ledger!$F:$F,Ledger!$O:$O,$A5) -> 11770 | C5: =SUMIFS(Ledger!$E:$E,Ledger!$O:$O,$A5) -> 8557.37 | D5: =$B5-$C5 -> 3212.63 | E5: =SUMIFS(Ledger!$L:$L,Ledger!$O:$O,$A5) -> 128.04 | F5: =COUNTIFS(Ledger!$O:$O,$A5) -> 30
A6: 2025-10 | B6: =SUMIFS(Ledger!$F:$F,Ledger!$O:$O,$A6) -> 0 | C6: =SUMIFS(Ledger!$E:$E,Ledger!$O:$O,$A6) -> 878.96 | D6: =$B6-$C6 -> -878.96 | E6: =SUMIFS(Ledger!$L:$L,Ledger!$O:$O,$A6) -> 73.53 | F6: =COUNTIFS(Ledger!$O:$O,$A6) -> 11
A7: 2025-11 | B7: =SUMIFS(Ledger!$F:$F,Ledger!$O:$O,$A7) -> 7059 | C7: =SUMIFS(Ledger!$E:$E,Ledger!$O:$O,$A7) -> 6400.65 | D7: =$B7-$C7 -> 658.35 | E7: =SUMIFS(Ledger!$L:$L,Ledger!$O:$O,$A7) -> 68.8 | F7: =COUNTIFS(Ledger!$O:$O,$A7) -> 51
A8: 2025-12 | B8: =SUMIFS(Ledger!$F:$F,Ledger!$O:$O,$A8) -> 9022.35 | C8: =SUMIFS(Ledger!$E:$E,Ledger!$O:$O,$A8) -> 9734.33 | D8: =$B8-$C8 -> -711.98 | E8: =SUMIFS(Ledger!$L:$L,Ledger!$O:$O,$A8) -> 39 | F8: =COUNTIFS(Ledger!$O:$O,$A8) -> 77
A9: 2026-01 | B9: =SUMIFS(Ledger!$F:$F,Ledger!$O:$O,$A9) -> 5082.74 | C9: =SUMIFS(Ledger!$E:$E,Ledger!$O:$O,$A9) -> 3610.77 | D9: =$B9-$C9 -> 1471.97 | E9: =SUMIFS(Ledger!$L:$L,Ledger!$O:$O,$A9) -> 36.77 | F9: =COUNTIFS(Ledger!$O:$O,$A9) -> 18
A10: 2026-02 | B10: =SUMIFS(Ledger!$F:$F,Ledger!$O:$O,$A10) -> 13436.79 | C10: =SUMIFS(Ledger!$E:$E,Ledger!$O:$O,$A10) -> 15265.58 | D10: =$B10-$C10 -> -1828.79 | E10: =SUMIFS(Ledger!$L:$L,Ledger!$O:$O,$A10) -> 70.95 | F10: =COUNTIFS(Ledger!$O:$O,$A10) -> 72
A11: TOTAL | B11: =SUM(B2:B10) -> 68825.88 | C11: =SUM(C2:C10) -> 60554.3 | D11: =SUM(D2:D10) -> 8271.58 | E11: =SUM(E2:E10) -> 572.68

Sheet Categories
A1: category_draft | B1: total_withdrawals | C1: total_deposits | D1: gst_candidate | E1: n_txns | F1: share_of_outflow
A2: Associate-Inflow | B2: =SUMIFS(Ledger!$E:$E,Ledger!$H:$H,$A2) -> 0 | C2: =SUMIFS(Ledger!$F:$F,Ledger!$H:$H,$A2) -> 735 | D2: =SUMIFS(Ledger!$L:$L,Ledger!$H:$H,$A2) -> 0 | E2: =COUNTIFS(Ledger!$H:$H,$A2) -> 5 | F2: =IF(SUM(Ledger!$E:$E)=0,0,$B2/SUM(Ledger!$E:$E)) -> 0
A3: Associate-Payment | B3: =SUMIFS(Ledger!$E:$E,Ledger!$H:$H,$A3) -> 27582 | C3: =SUMIFS(Ledger!$F:$F,Ledger!$H:$H,$A3) -> 0 | D3: =SUMIFS(Ledger!$L:$L,Ledger!$H:$H,$A3) -> 0 | E3: =COUNTIFS(Ledger!$H:$H,$A3) -> 64 | F3: =IF(SUM(Ledger!$E:$E)=0,0,$B3/SUM(Ledger!$E:$E)) -> 0.45549201
A4: Bank-Interest-Fees | B4: =SUMIFS(Ledger!$E:$E,Ledger!$H:$H,$A4) -> 0.18 | C4: =SUMIFS(Ledger!$F:$F,Ledger!$H:$H,$A4) -> 0 | D4: =SUMIFS(Ledger!$L:$L,Ledger!$H:$H,$A4) -> 0 | E4: =COUNTIFS(Ledger!$H:$H,$A4) -> 1 | F4: =IF(SUM(Ledger!$E:$E)=0,0,$B4/SUM(Ledger!$E:$E)) -> 2.9725387e-06
A5: Drawing-Cash | B5: =SUMIFS(Ledger!$E:$E,Ledger!$H:$H,$A5) -> 7850 | C5: =SUMIFS(Ledger!$F:$F,Ledger!$H:$H,$A5) -> 0 | D5: =SUMIFS(Ledger!$L:$L,Ledger!$H:$H,$A5) -> 0 | E5: =COUNTIFS(Ledger!$H:$H,$A5) -> 8 | F5: =IF(SUM(Ledger!$E:$E)=0,0,$B5/SUM(Ledger!$E:$E)) -> 0.12963572
A6: Fuel | B6: =SUMIFS(Ledger!$E:$E,Ledger!$H:$H,$A6) -> 2259.03 | C6: =SUMIFS(Ledger!$F:$F,Ledger!$H:$H,$A6) -> 0 | D6: =SUMIFS(Ledger!$L:$L,Ledger!$H:$H,$A6) -> 205.36 | E6: =COUNTIFS(Ledger!$H:$H,$A6) -> 33 | F6: =IF(SUM(Ledger!$E:$E)=0,0,$B6/SUM(Ledger!$E:$E)) -> 0.037305856
A7: Groceries | B7: =SUMIFS(Ledger!$E:$E,Ledger!$H:$H,$A7) -> 310.59 | C7: =SUMIFS(Ledger!$F:$F,Ledger!$H:$H,$A7) -> 0 | D7: =SUMIFS(Ledger!$L:$L,Ledger!$H:$H,$A7) -> 0 | E7: =COUNTIFS(Ledger!$H:$H,$A7) -> 5 | F7: =IF(SUM(Ledger!$E:$E)=0,0,$B7/SUM(Ledger!$E:$E)) -> 0.0051291155
A8: Income-Candidate | B8: =SUMIFS(Ledger!$E:$E,Ledger!$H:$H,$A8) -> 0 | C8: =SUMIFS(Ledger!$F:$F,Ledger!$H:$H,$A8) -> 68090.88 | D8: =SUMIFS(Ledger!$L:$L,Ledger!$H:$H,$A8) -> 0 | E8: =COUNTIFS(Ledger!$H:$H,$A8) -> 36 | F8: =IF(SUM(Ledger!$E:$E)=0,0,$B8/SUM(Ledger!$E:$E)) -> 0
A9: Insurance | B9: =SUMIFS(Ledger!$E:$E,Ledger!$H:$H,$A9) -> 339.72 | C9: =SUMIFS(Ledger!$F:$F,Ledger!$H:$H,$A9) -> 0 | D9: =SUMIFS(Ledger!$L:$L,Ledger!$H:$H,$A9) -> 30.87 | E9: =COUNTIFS(Ledger!$H:$H,$A9) -> 3 | F9: =IF(SUM(Ledger!$E:$E)=0,0,$B9/SUM(Ledger!$E:$E)) -> 0.0056101714
A10: Materials-Tools | B10: =SUMIFS(Ledger!$E:$E,Ledger!$H:$H,$A10) -> 3241.13 | C10: =SUMIFS(Ledger!$F:$F,Ledger!$H:$H,$A10) -> 0 | D10: =SUMIFS(Ledger!$L:$L,Ledger!$H:$H,$A10) -> 294.64 | E10: =COUNTIFS(Ledger!$H:$H,$A10) -> 24 | F10: =IF(SUM(Ledger!$E:$E)=0,0,$B10/SUM(Ledger!$E:$E)) -> 0.053524357
A11: Misc | B11: =SUMIFS(Ledger!$E:$E,Ledger!$H:$H,$A11) -> 17831.85 | C11: =SUMIFS(Ledger!$F:$F,Ledger!$H:$H,$A11) -> 0 | D11: =SUMIFS(Ledger!$L:$L,Ledger!$H:$H,$A11) -> 0 | E11: =COUNTIFS(Ledger!$H:$H,$A11) -> 97 | F11: =IF(SUM(Ledger!$E:$E)=0,0,$B11/SUM(Ledger!$E:$E)) -> 0.29447702
A12: Phone-Internet | B12: =SUMIFS(Ledger!$E:$E,Ledger!$H:$H,$A12) -> 60 | C12: =SUMIFS(Ledger!$F:$F,Ledger!$H:$H,$A12) -> 0 | D12: =SUMIFS(Ledger!$L:$L,Ledger!$H:$H,$A12) -> 5.46 | E12: =COUNTIFS(Ledger!$H:$H,$A12) -> 2 | F12: =IF(SUM(Ledger!$E:$E)=0,0,$B12/SUM(Ledger!$E:$E)) -> 0.00099084623
A13: Software-Subscriptions | B13: =SUMIFS(Ledger!$E:$E,Ledger!$H:$H,$A13) -> 200.28 | C13: =SUMIFS(Ledger!$F:$F,Ledger!$H:$H,$A13) -> 0 | D13: =SUMIFS(Ledger!$L:$L,Ledger!$H:$H,$A13) -> 18.19 | E13: =COUNTIFS(Ledger!$H:$H,$A13) -> 7 | F13: =IF(SUM(Ledger!$E:$E)=0,0,$B13/SUM(Ledger!$E:$E)) -> 0.0033074447
... A15: Vehicle-Tolls | B15: =SUMIFS(Ledger!$E:$E,Ledger!$H:$H,$A15) -> 200 | C15: =SUMIFS(Ledger!$F:$F,Ledger!$H:$H,$A15) -> 0 | D15: =SUMIFS(Ledger!$L:$L,Ledger!$H:$H,$A15) -> 18.16 | E15: =COUNTIFS(Ledger!$H:$H,$A15) -> 8 | F15: =IF(SUM(Ledger!$E:$E)=0,0,$B15/SUM(Ledger!$E:$E)) -> 0.0033028208

Sheet Flags
A1: flag_summary | B1: count
A2: DIV7A-CANDIDATE | B2: =COUNTIF(Ledger!$M:$M,"*DIV7A*") -> 64
A3: ASSOCIATE (any) | B3: =COUNTIF(Ledger!$M:$M,"*ASSOCIATE*") -> 69
A4: AUSTRAC>=10k | B4: =COUNTIF(Ledger!$M:$M,"*AUSTRAC*") -> 0
A5: REMITTANCE-REVIEW | B5: =COUNTIF(Ledger!$M:$M,"*REMITTANCE*") -> 0
A6: REZA-IDENTITY(OQ7) | B6: =COUNTIF(Ledger!$M:$M,"*REZA*") -> 4
A8: Flagged rows (derived view — source of truth = Ledger sheet):
A9: txn_id | B9: date | C9: description | D9: withdrawal | E9: deposit | F9: flags
A10: ANZ-BE-398c9c00bcf4 | B10: 2024-03-25 | C10: ANZ MOBILE BANKING PAYMENT 581694 | TO ARMIN MOHEBIAFZAP | EFFECTIVE DATE 23 MAR | D10: 500 | E10: 0 | F10: ASSOCIATE:Armin;DIV7A-CANDIDATE
A11: ANZ-BE-b1a65481cf1e | B11: 2024-03-26 | C11: ANZ MOBILE BANKING PAYMENT 088730 | TO ARMIN MOHEBIAFZAP | D11: 100 | E11: 0 | F11: ASSOCIATE:Armin;DIV7A-CANDIDATE
A12: ANZ-BE-0047cdc2e66a | B12: 2024-03-26 | C12: ANZ MOBILE BANKING PAYMENT 583363 | TO ARMIN MOHEBIAFZAP | D12: 150 | E12: 0 | F12: ASSOCIATE:Armin;DIV7A-CANDIDATE
A13: ANZ-BE-efb9333410e8 | B13: 2024-03-26 | C13: ANZ MOBILE BANKING PAYMENT 746999 | TO ARMIN MOHEBIAFZAP | D13: 400 | E13: 0 | F13: ASSOCIATE:Armin;DIV7A-CANDIDATE
A14: ANZ-BE-7bead8d82347 | B14: 2024-03-27 | C14: ANZ MOBILE BANKING PAYMENT 062502 | TO ARMIN MOHEBIAFZAP | D14: 200 | E14: 0 | F14: ASSOCIATE:Armin;DIV7A-CANDIDATE
A15: ANZ-BE-64a8a265a197 | B15: 2024-04-02 | C15: ANZ MOBILE BANKING PAYMENT 139859 | TO ARMIN MOHEBIAFZAP | EFFECTIVE DATE 29 MAR | D15: 150 | E15: 0 | F15: ASSOCIATE:Armin;DIV7A-CANDIDATE
A16: ANZ-BE-ba0dcd18960a | B16: 2024-04-02 | C16: ANZ MOBILE BANKING PAYMENT 206793 | TO ARMIN MOHEBIAFZAP | EFFECTIVE DATE 30 MAR | D16: 670 | E16: 0 | F16: ASSOCIATE:Armin;DIV7A-CANDIDATE
A17: ANZ-BE-840be53a709a | B17: 2024-04-02 | C17: ANZ MOBILE BANKING PAYMENT 908897 | TO ARMIN MOHEBIAFZAP | D17: 1173 | E17: 0 | F17: ASSOCIATE:Armin;DIV7A-CANDIDATE
A18: ANZ-BE-b1e61b4e660a | B18: 2024-04-03 | C18: ANZ MOBILE BANKING PAYMENT 405863 | TO ARMIN MOHEBIAFZAP | D18: 50 | E18: 0 | F18: ASSOCIATE:Armin;DIV7A-CANDIDATE
A19: ANZ-BE-bdd663851062 | B19: 2024-04-03 | C19: ANZ MOBILE BANKING PAYMENT 407124 | TO ARMIN MOHEBIAFZAP | D19: 500 | E19: 0 | F19: ASSOCIATE:Armin;DIV7A-CANDIDATE
A20: ANZ-BE-e5d7646a95fc | B20: 2024-04-04 | C20: ANZ MOBILE BANKING PAYMENT 160491 | TO ARMIN MOHEBIAFZAP | D20: 600 | E20: 0 | F20: ASSOCIATE:Armin;DIV7A-CANDIDATE
A21: ANZ-BE-433634a4821b | B21: 2024-04-05 | C21: ANZ MOBILE BANKING PAYMENT 380416 | TO ARMIN MOHEBIAFZAP | D21: 20 | E21: 0 | F21: ASSOCIATE:Armin;DIV7A-CANDIDATE
... A82: ANZ-BE-3cb92ce13f80 | B82: 2026-02-20 | C82: ANZ MOBILE BANKING PAYMENT 146377 | TO ARMIN MOHEBIAFZAP | D82: 470 | E82: 0 | F82: ASSOCIATE:Armin;DIV7A-CANDIDATE

Sheet Recon
A1: from_stmt | B1: to_stmt | C1: missing_between | D1: closing | E1: next_opening | F1: continuous
A2: 4 | B2: 8 | C2: 3 | D2: 7098.75 | E2: 0.58 | F2: n/a (gap)
A3: 8 | B3: 23 | C3: 14 | D3: 5240.03 | E3: 1937.84 | F3: n/a (gap)
A4: 23 | B4: 24 | C4: 0 | D4: 1493.32 | E4: 1493.32 | F4: YES
A5: 24 | B5: 26 | C5: 1 | D5: 1005.25 | E5: 695.95 | F5: n/a (gap)
A8: Dedup log: 0 duplicates removed this run (periods are disjoint; hash IDs guarantee idempotent re-ingest).
